astro_what/__init__.py
astro_what/cli.py
astro_what/core.py
astro_what/moon_tools.py
astro_what-0.1.4.dist-info/licenses/LICENSE
astro_what-0.1.4.dist-info/METADATA
astro_what-0.1.4.dist-info/WHEEL
astro_what-0.1.4.dist-info/entry_points.txt
astro_what-0.1.4.dist-info/top_level.txt
astro_what-0.1.4.dist-info/RECORD
